<DocumentElement><Orders><Order><OrderNumber>PO000593</OrderNumber><Description>JOLIN20 PRODUCTION LEADER 20230523-HARVEST AGENCY</Description><CurrencyCode>SEK</CurrencyCode><InvoicingSupplierCode>SUIMVRRRTI</InvoicingSupplierCode><MainSupplierCode>SUIMVRRRTI</MainSupplierCode><OrganizationElementCode>4130</OrganizationElementCode><CompanyCode>4130</CompanyCode><NetSum>145600.00</NetSum><OwnerName>Jonas Lind&#233;n jonas.linden1@inter.ikea.com</OwnerName><BuyerName>Lina Karlsson lina.karlsson@inter.ikea.com</BuyerName><IssueDate>2023-05-23T09:14:55</IssueDate><Created>2023-05-23T08:50:16</Created><POSourceSystem>IVALUA</POSourceSystem><Text9 /><Text10>PO000593</Text10><Deleted>false</Deleted><GoodsReceiptsBasedInvoicing>true</GoodsReceiptsBasedInvoicing><Closed>false</Closed><MatchingMode>0</MatchingMode><Text8>https://copp.inter.ikea.com/page.aspx/en/ord/order_manage/593</Text8><OrderRows><OrderRow><OrderNumber>PO000593</OrderNumber><RowIndex>3841</RowIndex><Text10>3841</Text10><SortNumber>1</SortNumber><Quantity>224.0000000000</Quantity><UnitCode>HUR</UnitCode><NetPrice>650.0000000000</NetPrice><NetSum>145600.000000</NetSum><ProductCode>CW_PS_177</ProductCode><ProductName>Production Leader - Expert </ProductName><Comment>PETER TURKALJ - PRODUCTION LEADER

Note* Please d</Comment><Description>Production Leader - Expert </Description><MatchingMode>0</MatchingMode><GoodsReceiptsBasedInvoicing>false</GoodsReceiptsBasedInvoicing><ReceiveMethod>1</ReceiveMethod><Deleted>false</Deleted><Closed>false</Closed><OverReceivalAllowed>1</OverReceivalAllowed><Numeric5>1</Numeric5><GoodsReceiptRequired>true</GoodsReceiptRequired><Text6>PRS4</Text6><Text7>BSU009</Text7><Text4>CC7647</Text4><CodingRows><CodingRow><OrderNumber>PO000593</OrderNumber><OrderRowNumber>3841</OrderRowNumber><RowIndex>1</RowIndex><BudgetCode>PRS4</BudgetCode><BusinessUnitCode>BSU009</BusinessUnitCode><CostCenterCode>CC7647</CostCenterCode><NetSum>145600.000000</NetSum></CodingRow></CodingRows></OrderRow></OrderRows></Order></Orders></DocumentElement>